[
	{
		"inputs": [],
		"stateMutability": "nonpayable",
		"type": "constructor"
	},
	{
		"anonymous": false,
		"inputs": [
			{
				"indexed": false,
				"internalType": "address",
				"name": "ipAddr",
				"type": "address"
			},
			{
				"indexed": false,
				"internalType": "uint256",
				"name": "amount",
				"type": "uint256"
			}
		],
		"name": "AddLiquidity",
		"type": "event"
	},
	{
		"anonymous": false,
		"inputs": [
			{
				"indexed": false,
				"internalType": "bytes32",
				"name": "orderId",
				"type": "bytes32"
			},
			{
				"indexed": false,
				"internalType": "uint8",
				"name": "state",
				"type": "uint8"
			},
			{
				"indexed": false,
				"internalType": "uint256",
				"name": "totalAmount",
				"type": "uint256"
			}
		],
		"name": "ChangeOrder",
		"type": "event"
	},
	{
		"anonymous": false,
		"inputs": [
			{
				"indexed": false,
				"internalType": "bytes32",
				"name": "orderId",
				"type": "bytes32"
			},
			{
				"indexed": false,
				"internalType": "address",
				"name": "buyerAddr",
				"type": "address"
			},
			{
				"indexed": false,
				"internalType": "address",
				"name": "productAddr",
				"type": "address"
			},
			{
				"indexed": false,
				"internalType": "uint256",
				"name": "amount",
				"type": "uint256"
			},
			{
				"indexed": false,
				"internalType": "uint256",
				"name": "price",
				"type": "uint256"
			}
		],
		"name": "NewOrder",
		"type": "event"
	},
	{
		"anonymous": false,
		"inputs": [
			{
				"indexed": true,
				"internalType": "address",
				"name": "previousOwner",
				"type": "address"
			},
			{
				"indexed": true,
				"internalType": "address",
				"name": "newOwner",
				"type": "address"
			}
		],
		"name": "OwnershipTransferred",
		"type": "event"
	},
	{
		"anonymous": false,
		"inputs": [
			{
				"indexed": false,
				"internalType": "address",
				"name": "account",
				"type": "address"
			}
		],
		"name": "Paused",
		"type": "event"
	},
	{
		"anonymous": false,
		"inputs": [
			{
				"indexed": false,
				"internalType": "address",
				"name": "account",
				"type": "address"
			}
		],
		"name": "Unpaused",
		"type": "event"
	},
	{
		"anonymous": false,
		"inputs": [
			{
				"indexed": false,
				"internalType": "address",
				"name": "ipAddr",
				"type": "address"
			},
			{
				"indexed": false,
				"internalType": "uint256",
				"name": "amount",
				"type": "uint256"
			}
		],
		"name": "WithdrawLiquidity",
		"type": "event"
	},
	{
		"inputs": [],
		"name": "EtherUnit",
		"outputs": [
			{
				"internalType": "uint256",
				"name": "",
				"type": "uint256"
			}
		],
		"stateMutability": "view",
		"type": "function"
	},
	{
		"inputs": [
			{
				"internalType": "address",
				"name": "_providerAddr",
				"type": "address"
			}
		],
		"name": "InsuranceProviderPoolInfo",
		"outputs": [
			{
				"internalType": "uint256",
				"name": "avail",
				"type": "uint256"
			},
			{
				"internalType": "uint256",
				"name": "locked",
				"type": "uint256"
			}
		],
		"stateMutability": "view",
		"type": "function"
	},
	{
		"inputs": [],
		"name": "OrderIndex",
		"outputs": [
			{
				"internalType": "uint256",
				"name": "",
				"type": "uint256"
			}
		],
		"stateMutability": "view",
		"type": "function"
	},
	{
		"inputs": [],
		"name": "addLiquidityEth",
		"outputs": [
			{
				"internalType": "bool",
				"name": "",
				"type": "bool"
			}
		],
		"stateMutability": "payable",
		"type": "function"
	},
	{
		"inputs": [
			{
				"internalType": "address",
				"name": "_productOwner",
				"type": "address"
			},
			{
				"internalType": "string",
				"name": "_productName",
				"type": "string"
			},
			{
				"internalType": "uint256",
				"name": "_feeRate",
				"type": "uint256"
			},
			{
				"internalType": "uint256",
				"name": "_status",
				"type": "uint256"
			}
		],
		"name": "addProduct",
		"outputs": [],
		"stateMutability": "nonpayable",
		"type": "function"
	},
	{
		"inputs": [
			{
				"internalType": "address",
				"name": "_productAddr",
				"type": "address"
			},
			{
				"internalType": "uint256",
				"name": "_amount",
				"type": "uint256"
			},
			{
				"internalType": "uint256",
				"name": "_blocks",
				"type": "uint256"
			},
			{
				"internalType": "address payable[]",
				"name": "_ipAddrs",
				"type": "address[]"
			},
			{
				"internalType": "uint256[]",
				"name": "_ipAmount",
				"type": "uint256[]"
			}
		],
		"name": "buyInsurance",
		"outputs": [
			{
				"internalType": "bytes32",
				"name": "_orderId",
				"type": "bytes32"
			}
		],
		"stateMutability": "payable",
		"type": "function"
	},
	{
		"inputs": [
			{
				"internalType": "address",
				"name": "_productOwner",
				"type": "address"
			}
		],
		"name": "deleteProduct",
		"outputs": [],
		"stateMutability": "nonpayable",
		"type": "function"
	},
	{
		"inputs": [],
		"name": "ethPool",
		"outputs": [
			{
				"internalType": "uint256",
				"name": "avail",
				"type": "uint256"
			},
			{
				"internalType": "uint256",
				"name": "locked",
				"type": "uint256"
			}
		],
		"stateMutability": "view",
		"type": "function"
	},
	{
		"inputs": [],
		"name": "getMine",
		"outputs": [
			{
				"internalType": "contract INSureToken",
				"name": "",
				"type": "address"
			}
		],
		"stateMutability": "view",
		"type": "function"
	},
	{
		"inputs": [
			{
				"internalType": "address",
				"name": "_productOwner",
				"type": "address"
			}
		],
		"name": "getProduct",
		"outputs": [
			{
				"components": [
					{
						"internalType": "string",
						"name": "productName",
						"type": "string"
					},
					{
						"internalType": "uint256",
						"name": "feeRate",
						"type": "uint256"
					},
					{
						"internalType": "uint256",
						"name": "status",
						"type": "uint256"
					},
					{
						"internalType": "uint256",
						"name": "totalPremium",
						"type": "uint256"
					},
					{
						"internalType": "uint256",
						"name": "totalSale",
						"type": "uint256"
					}
				],
				"internalType": "struct NSure.Product",
				"name": "",
				"type": "tuple"
			}
		],
		"stateMutability": "view",
		"type": "function"
	},
	{
		"inputs": [
			{
				"internalType": "bytes32",
				"name": "",
				"type": "bytes32"
			}
		],
		"name": "insuranceOrders",
		"outputs": [
			{
				"internalType": "address payable",
				"name": "buyer",
				"type": "address"
			},
			{
				"internalType": "uint256",
				"name": "premium",
				"type": "uint256"
			},
			{
				"internalType": "uint256",
				"name": "price",
				"type": "uint256"
			},
			{
				"internalType": "uint8",
				"name": "state",
				"type": "uint8"
			},
			{
				"internalType": "uint256",
				"name": "settleBlockNumber",
				"type": "uint256"
			},
			{
				"internalType": "uint256",
				"name": "totalProvider",
				"type": "uint256"
			}
		],
		"stateMutability": "view",
		"type": "function"
	},
	{
		"inputs": [],
		"name": "owner",
		"outputs": [
			{
				"internalType": "address",
				"name": "",
				"type": "address"
			}
		],
		"stateMutability": "view",
		"type": "function"
	},
	{
		"inputs": [],
		"name": "paused",
		"outputs": [
			{
				"internalType": "bool",
				"name": "",
				"type": "bool"
			}
		],
		"stateMutability": "view",
		"type": "function"
	},
	{
		"inputs": [],
		"name": "renounceOwnership",
		"outputs": [],
		"stateMutability": "nonpayable",
		"type": "function"
	},
	{
		"inputs": [
			{
				"internalType": "contract INSureToken",
				"name": "newMine",
				"type": "address"
			}
		],
		"name": "setMine",
		"outputs": [],
		"stateMutability": "nonpayable",
		"type": "function"
	},
	{
		"inputs": [
			{
				"internalType": "uint256",
				"name": "_amount",
				"type": "uint256"
			}
		],
		"name": "setMinimumDeposit",
		"outputs": [],
		"stateMutability": "nonpayable",
		"type": "function"
	},
	{
		"inputs": [
			{
				"internalType": "bytes32",
				"name": "_orderId",
				"type": "bytes32"
			}
		],
		"name": "setOrderFinished",
		"outputs": [
			{
				"internalType": "bool",
				"name": "",
				"type": "bool"
			}
		],
		"stateMutability": "nonpayable",
		"type": "function"
	},
	{
		"inputs": [
			{
				"internalType": "bytes32",
				"name": "_orderId",
				"type": "bytes32"
			}
		],
		"name": "setOrderWithClaims",
		"outputs": [
			{
				"internalType": "bool",
				"name": "",
				"type": "bool"
			}
		],
		"stateMutability": "nonpayable",
		"type": "function"
	},
	{
		"inputs": [
			{
				"internalType": "address payable",
				"name": "newAddr",
				"type": "address"
			}
		],
		"name": "setStakingAddr",
		"outputs": [],
		"stateMutability": "nonpayable",
		"type": "function"
	},
	{
		"inputs": [],
		"name": "teamPremium",
		"outputs": [
			{
				"internalType": "uint256",
				"name": "",
				"type": "uint256"
			}
		],
		"stateMutability": "view",
		"type": "function"
	},
	{
		"inputs": [
			{
				"internalType": "address",
				"name": "newOwner",
				"type": "address"
			}
		],
		"name": "transferOwnership",
		"outputs": [],
		"stateMutability": "nonpayable",
		"type": "function"
	},
	{
		"inputs": [
			{
				"internalType": "address",
				"name": "_productOwner",
				"type": "address"
			},
			{
				"internalType": "string",
				"name": "_productName",
				"type": "string"
			},
			{
				"internalType": "uint256",
				"name": "_feeRate",
				"type": "uint256"
			},
			{
				"internalType": "uint256",
				"name": "_status",
				"type": "uint256"
			}
		],
		"name": "updateProduct",
		"outputs": [],
		"stateMutability": "nonpayable",
		"type": "function"
	},
	{
		"inputs": [
			{
				"internalType": "uint256",
				"name": "_amount",
				"type": "uint256"
			}
		],
		"name": "withdrawLiquidity",
		"outputs": [
			{
				"internalType": "bool",
				"name": "",
				"type": "bool"
			}
		],
		"stateMutability": "nonpayable",
		"type": "function"
	},
	{
		"inputs": [
			{
				"internalType": "uint256",
				"name": "amount",
				"type": "uint256"
			}
		],
		"name": "withdrawPremium",
		"outputs": [],
		"stateMutability": "nonpayable",
		"type": "function"
	},
	{
		"stateMutability": "payable",
		"type": "receive"
	}
]